setup.py
custom/__init__.py
custom.egg-info/PKG-INFO
custom.egg-info/SOURCES.txt
custom.egg-info/dependency_links.txt
custom.egg-info/top_level.txt
custom/CustomCarry/__init__.py
custom/CustomCarry/custom.py
custom/CustomCarry/test.py