Metadata-Version: 1.0
Name: custom
Version: 0.1.1
Summary: Custom self carry
Home-page: https://github.com/flytrap/custom
Author: flytrap
Author-email: hiddes@126.com
License: UNKNOWN
Platform: UNKNOWN
